[
{"Name": "Andaman & Nicobar Islands", "Status": "Union Territory", "Population1": "280,661", "Population2": "356,152", "Population3": "380,581"},
{"Name": "Nicobar", "Status": "District", "Population1": "39,208", "Population2": "42,068", "Population3": "36,842"},
{"Name": "North  & Middle Andaman", "Status": "District", "Population1": "...", "Population2": "105,613", "Population3": "105,597"},
{"Name": "South Andaman", "Status": "District", "Population1": "...", "Population2": "208,471", "Population3": "238,142"},
{"Name": "Andhra Pradesh", "Status": "State", "Population1": "40,419,034", "Population2": "45,397,069", "Population3": "49,577,103"},
{"Name": "Anantapur", "Status": "District", "Population1": "3,183,814", "Population2": "3,640,478", "Population3": "4,081,148"},
{"Name": "Chittoor", "Status": "District", "Population1": "3,261,118", "Population2": "3,745,875", "Population3": "4,174,064"},
{"Name": "East Godavari", "Status": "District", "Population1": "...", "Population2": "5,021,502", "Population3": "5,285,824"},
{"Name": "Guntur", "Status": "District", "Population1": "4,106,999", "Population2": "4,465,144", "Population3": "4,887,813"},
{"Name": "Krishna", "Status": "District", "Population1": "3,698,933", "Population2": "4,187,841", "Population3": "4,517,398"},
{"Name": "Kurnool", "Status": "District", "Population1": "2,973,024", "Population2": "3,529,494", "Population3": "4,053,463"},
{"Name": "Prakasam", "Status": "District", "Population1": "2,759,166", "Population2": "3,059,423", "Population3": "3,397,448"},
{"Name": "Srikakulam", "Status": "District", "Population1": "2,321,126", "Population2": "2,537,593", "Population3": "2,703,114"},
{"Name": "Sri Potti Sriramulu Nellore", "Status": "District", "Population1": "2,392,260", "Population2": "2,668,564", "Population3": "2,963,557"},
{"Name": "Visakhapatnam", "Status": "District", "Population1": "3,285,092", "Population2": "3,832,336", "Population3": "4,290,589"},
{"Name": "Vizianagaram", "Status": "District", "Population1": "2,110,943", "Population2": "2,249,254", "Population3": "2,344,474"},
{"Name": "West Godavari", "Status": "District", "Population1": "...", "Population2": "3,857,768", "Population3": "3,995,742"},
{"Name": "Y.S.R.", "Status": "District", "Population1": "2,267,769", "Population2": "2,601,797", "Population3": "2,882,469"},
{"Name": "Arunachal Pradesh", "Status": "State", "Population1": "864,558", "Population2": "1,097,968", "Population3": "1,383,727"},
{"Name": "Anjaw", "Status": "District", "Population1": "17,188", "Population2": "18,536", "Population3": "21,167"},
{"Name": "Changlang", "Status": "District", "Population1": "95,530", "Population2": "125,422", "Population3": "148,226"},
{"Name": "Dibang Valley", "Status": " (", "Population1": ")", "Population2": "District", "Population3": "6,181"},
{"Name": "East Kameng", "Status": "District", "Population1": "50,395", "Population2": "57,179", "Population3": "78,690"},
{"Name": "East Siang", "Status": "District", "Population1": "...", "Population2": "62,950", "Population3": "70,956"},
{"Name": "Kra Daadi", "Status": " (", "Population1": ")", "Population2": "District", "Population3": "..."},
{"Name": "Kurung Kumey", "Status": "District", "Population1": "...", "Population2": "24,676", "Population3": "45,372"},
{"Name": "Lohit", "Status": "District", "Population1": "...", "Population2": "42,833", "Population3": "49,776"},
{"Name": "Longding", "Status": " (", "Population1": ")", "Population2": "District", "Population3": "..."},
{"Name": "Lower Dibang Valley", "Status": "District", "Population1": "36,888", "Population2": "50,448", "Population3": "54,080"},
{"Name": "Lower Siang", "Status": " (", "Population1": ")", "Population2": "District", "Population3": "..."},
{"Name": "Lower Subansiri", "Status": "District", "Population1": "43,148", "Population2": "55,726", "Population3": "83,030"},
{"Name": "Namsai", "Status": " (", "Population1": ")", "Population2": "District", "Population3": "..."},
{"Name": "Papum Pare", "Status": "District", "Population1": "72,811", "Population2": "122,003", "Population3": "176,573"},
{"Name": "Siang", "Status": " (", "Population1": ")", "Population2": "District", "Population3": "..."},
{"Name": "Tawang", "Status": "District", "Population1": "28,287", "Population2": "38,924", "Population3": "49,977"},
{"Name": "Tirap", "Status": "District", "Population1": "...", "Population2": "49,304", "Population3": "55,022"},
{"Name": "Upper Siang", "Status": "District", "Population1": "27,779", "Population2": "33,363", "Population3": "35,320"},
{"Name": "Upper Subansiri", "Status": "District", "Population1": "50,086", "Population2": "55,346", "Population3": "83,448"},
{"Name": "West Kameng", "Status": "District", "Population1": "56,421", "Population2": "74,599", "Population3": "83,947"},
{"Name": "West Siang", "Status": "District", "Population1": "...", "Population2": "63,993", "Population3": "71,492"},
{"Name": "Assam", "Status": "State", "Population1": "22,414,322", "Population2": "26,655,528", "Population3": "31,205,576"},
{"Name": "Baksa", "Status": "District", "Population1": "762,600", "Population2": "857,947", "Population3": "950,075"},
{"Name": "Barpeta", "Status": "District", "Population1": "1,166,000", "Population2": "1,394,755", "Population3": "1,693,622"},
{"Name": "Biswanath", "Status": " (", "Population1": ")", "Population2": "District", "Population3": "..."},
{"Name": "Bongaigaon", "Status": "District", "Population1": "501,800", "Population2": "612,665", "Population3": "738,804"},
{"Name": "Cachar", "Status": "District", "Population1": "1,215,300", "Population2": "1,444,921", "Population3": "1,736,617"},
{"Name": "Charaideo", "Status": " (", "Population1": ")", "Population2": "District", "Population3": "..."},
{"Name": "Chirang", "Status": "District", "Population1": "433,400", "Population2": "433,061", "Population3": "482,162"},
{"Name": "Darrang", "Status": "District", "Population1": "621,900", "Population2": "759,858", "Population3": "928,500"},
{"Name": "Dhemaji", "Status": "District", "Population1": "478,800", "Population2": "571,944", "Population3": "686,133"},
{"Name": "Dhubri", "Status": "District", "Population1": "...", "Population2": "1,127,572", "Population3": "1,394,144"},
{"Name": "Dibrugarh", "Status": "District", "Population1": "1,042,500", "Population2": "1,185,072", "Population3": "1,326,335"},
{"Name": "Dima Hasao", "Status": "District", "Population1": "150,800", "Population2": "188,079", "Population3": "214,102"},
{"Name": "Goalpara", "Status": "District", "Population1": "668,200", "Population2": "822,035", "Population3": "1,008,183"},
{"Name": "Golaghat", "Status": "District", "Population1": "828,096", "Population2": "946,279", "Population3": "1,066,888"},
{"Name": "Hailakandi", "Status": "District", "Population1": "449,100", "Population2": "542,872", "Population3": "659,296"},
{"Name": "Hojai", "Status": " (", "Population1": ")", "Population2": "District", "Population3": "..."},
{"Name": "Jorhat", "Status": "District", "Population1": "...", "Population2": "845,821", "Population3": "924,952"},
{"Name": "Kamrup", "Status": "District", "Population1": "1,140,900", "Population2": "1,311,698", "Population3": "1,517,542"},
{"Name": "Kamrup Metropolitan", "Status": "District", "Population1": "726,200", "Population2": "1,059,578", "Population3": "1,253,938"},
{"Name": "Karbi Anglong", "Status": "District", "Population1": "...", "Population2": "566,142", "Population3": "660,955"},
{"Name": "Karimganj", "Status": "District", "Population1": "827,100", "Population2": "1,007,976", "Population3": "1,228,686"},
{"Name": "Kokrajhar", "Status": "District", "Population1": "736,500", "Population2": "843,243", "Population3": "887,142"},
{"Name": "Lakhimpur", "Status": "District", "Population1": "751,500", "Population2": "889,010", "Population3": "1,042,137"},
{"Name": "Majuli", "Status": " (", "Population1": ")", "Population2": "District", "Population3": "..."},
{"Name": "Morigaon", "Status": "District", "Population1": "639,700", "Population2": "776,256", "Population3": "957,423"},
{"Name": "Nagaon", "Status": "District", "Population1": "...", "Population2": "1,569,838", "Population3": "1,892,550"},
{"Name": "Nalbari", "Status": "District", "Population1": "603,300", "Population2": "689,053", "Population3": "771,639"},
{"Name": "Sivasagar", "Status": "District", "Population1": "...", "Population2": "636,805", "Population3": "692,435"},
{"Name": "Sonitpur", "Status": "District", "Population1": "...", "Population2": "1,126,231", "Population3": "1,311,619"},
{"Name": "South Salmara-Mankachar", "Status": " (", "Population1": ")", "Population2": "District", "Population3": "..."},
{"Name": "Tinsukia", "Status": "District", "Population1": "962,300", "Population2": "1,150,062", "Population3": "1,327,929"},
{"Name": "Udalguri", "Status": "District", "Population1": "689,600", "Population2": "758,746", "Population3": "831,668"},
{"Name": "West Karbi Anglong", "Status": " (", "Population1": ")", "Population2": "District", "Population3": "..."},
{"Name": "Bihar", "Status": "State", "Population1": "64,530,554", "Population2": "82,998,509", "Population3": "104,099,452"},
{"Name": "Araria", "Status": "District", "Population1": "1,611,638", "Population2": "2,158,608", "Population3": "2,811,569"},
{"Name": "Arwal", "Status": "District", "Population1": "...", "Population2": "588,124", "Population3": "700,843"},
{"Name": "Aurangabad", "Status": "District", "Population1": "1,539,988", "Population2": "2,013,055", "Population3": "2,540,073"},
{"Name": "Banka", "Status": "District", "Population1": "1,292,504", "Population2": "1,608,773", "Population3": "2,034,763"},
{"Name": "Begusarai", "Status": "District", "Population1": "1,814,773", "Population2": "2,349,366", "Population3": "2,970,541"},
{"Name": "Bhagalpur", "Status": "District", "Population1": "1,909,967", "Population2": "2,423,172", "Population3": "3,037,766"},
{"Name": "Bhojpur", "Status": "District", "Population1": "1,792,771", "Population2": "2,243,144", "Population3": "2,728,407"},
{"Name": "Buxar", "Status": "District", "Population1": "1,087,676", "Population2": "1,402,396", "Population3": "1,706,352"},
{"Name": "Darbhanga", "Status": "District", "Population1": "2,510,959", "Population2": "3,295,789", "Population3": "3,937,385"},
{"Name": "Gaya", "Status": "District", "Population1": "2,664,803", "Population2": "3,473,428", "Population3": "4,391,418"},
{"Name": "Gopalganj", "Status": "District", "Population1": "1,704,310", "Population2": "2,152,638", "Population3": "2,562,012"},
{"Name": "Jamui", "Status": "District", "Population1": "1,051,527", "Population2": "1,398,796", "Population3": "1,760,405"},
{"Name": "Jehanabad", "Status": "District", "Population1": "...", "Population2": "926,191", "Population3": "1,125,313"},
{"Name": "Kaimur", "Status": "District", "Population1": "983,269", "Population2": "1,275,579", "Population3": "1,626,384"},
{"Name": "Katihar", "Status": "District", "Population1": "1,825,380", "Population2": "2,392,638", "Population3": "3,071,029"},
{"Name": "Khagaria", "Status": "District", "Population1": "987,227", "Population2": "1,280,354", "Population3": "1,666,886"},
{"Name": "Kishanganj", "Status": "District", "Population1": "984,107", "Population2": "1,296,348", "Population3": "1,690,400"},
{"Name": "Lakhisarai", "Status": "District", "Population1": "646,395", "Population2": "802,225", "Population3": "1,000,912"},
{"Name": "Madhepura", "Status": "District", "Population1": "1,177,706", "Population2": "1,526,646", "Population3": "2,001,762"},
{"Name": "Madhubani", "Status": "District", "Population1": "2,832,024", "Population2": "3,575,281", "Population3": "4,487,379"},
{"Name": "Munger", "Status": "District", "Population1": "943,583", "Population2": "1,137,797", "Population3": "1,367,765"},
{"Name": "Muzaffarpur", "Status": "District", "Population1": "2,953,903", "Population2": "3,746,714", "Population3": "4,801,062"},
{"Name": "Nalanda", "Status": "District", "Population1": "1,996,257", "Population2": "2,370,528", "Population3": "2,877,653"},
{"Name": "Nawada", "Status": "District", "Population1": "1,359,694", "Population2": "1,809,696", "Population3": "2,219,146"},
{"Name": "Pashchim Champaran", "Status": "District", "Population1": "2,333,666", "Population2": "3,043,466", "Population3": "3,935,042"},
{"Name": "Patna", "Status": "District", "Population1": "3,618,211", "Population2": "4,718,592", "Population3": "5,838,465"},
{"Name": "Purba Champaran", "Status": "District", "Population1": "3,043,061", "Population2": "3,939,773", "Population3": "5,099,371"},
{"Name": "Purnia", "Status": "District", "Population1": "1,878,885", "Population2": "2,543,942", "Population3": "3,264,619"},
{"Name": "Rohtas", "Status": "District", "Population1": "1,917,416", "Population2": "2,464,243", "Population3": "2,959,918"},
{"Name": "Saharsa", "Status": "District", "Population1": "1,132,413", "Population2": "1,508,182", "Population3": "1,900,661"},
{"Name": "Samastipur", "Status": "District", "Population1": "2,716,929", "Population2": "3,394,793", "Population3": "4,261,566"},
{"Name": "Saran", "Status": "District", "Population1": "2,572,980", "Population2": "3,248,701", "Population3": "3,951,862"},
{"Name": "Sheikhpura", "Status": "District", "Population1": "420,260", "Population2": "525,502", "Population3": "636,342"},
{"Name": "Sheohar", "Status": "District", "Population1": "377,699", "Population2": "515,961", "Population3": "656,246"},
{"Name": "Sitamarhi", "Status": "District", "Population1": "2,013,796", "Population2": "2,682,720", "Population3": "3,423,574"},
{"Name": "Siwan", "Status": "District", "Population1": "2,170,971", "Population2": "2,714,349", "Population3": "3,330,464"},
{"Name": "Supaul", "Status": "District", "Population1": "1,342,841", "Population2": "1,732,578", "Population3": "2,229,076"},
{"Name": "Vaishali", "Status": "District", "Population1": "2,146,065", "Population2": "2,718,421", "Population3": "3,495,021"},
{"Name": "Chandigarh", "Status": "Union Territory", "Population1": "642,015", "Population2": "900,635", "Population3": "1,055,450"},
{"Name": "Chandigarh", "Status": "Union Territory", "Population1": "642,015", "Population2": "900,635", "Population3": "1,055,450"},
{"Name": "Chhattisgarh", "Status": "State", "Population1": "17,614,928", "Population2": "20,833,803", "Population3": "25,545,198"},
{"Name": "Balod", "Status": " (", "Population1": ")", "Population2": "District", "Population3": "..."},
{"Name": "Baloda Bazar", "Status": " (", "Population1": ")", "Population2": "District", "Population3": "..."},
{"Name": "Balrampur", "Status": " (", "Population1": ")", "Population2": "District", "Population3": "..."},
{"Name": "Bastar", "Status": "District", "Population1": "...", "Population2": "706,656", "Population3": "834,375"},
{"Name": "Bemetara", "Status": " (", "Population1": ")", "Population2": "District", "Population3": "..."},
{"Name": "Bijapur", "Status": "District", "Population1": "...", "Population2": "234,637", "Population3": "255,230"},
{"Name": "Bilaspur", "Status": "District", "Population1": "...", "Population2": "1,490,921", "Population3": "1,961,922"},
{"Name": "Dakshin Bastar Dantewada", "Status": "District", "Population1": "...", "Population2": "244,834", "Population3": "283,479"},
{"Name": "Dhamtari", "Status": "District", "Population1": "587,679", "Population2": "706,591", "Population3": "799,781"},
{"Name": "Durg", "Status": "District", "Population1": "...", "Population2": "1,503,146", "Population3": "1,721,948"},
{"Name": "Gariaband", "Status": " (", "Population1": ")", "Population2": "District", "Population3": "..."},
{"Name": "Janjgir-Champa", "Status": "District", "Population1": "1,110,200", "Population2": "1,317,431", "Population3": "1,619,707"},
{"Name": "Jashpur", "Status": "District", "Population1": "656,352", "Population2": "743,160", "Population3": "851,669"},
{"Name": "Kabirdham", "Status": " (", "Population1": ")", "Population2": "District", "Population3": "513,496"},
{"Name": "Kondagaon", "Status": " (", "Population1": ")", "Population2": "District", "Population3": "..."},
{"Name": "Korba", "Status": "District", "Population1": "826,000", "Population2": "1,011,823", "Population3": "1,206,640"},
{"Name": "Koriya", "Status": "District", "Population1": "500,758", "Population2": "586,327", "Population3": "658,917"},
{"Name": "Mahasamund", "Status": "District", "Population1": "791,197", "Population2": "860,257", "Population3": "1,032,754"},
{"Name": "Mungeli", "Status": " (", "Population1": ")", "Population2": "District", "Population3": "..."},
{"Name": "Narayanpur", "Status": "District", "Population1": "...", "Population2": "117,337", "Population3": "139,820"},
{"Name": "Raigarh", "Status": "District", "Population1": "1,065,939", "Population2": "1,265,529", "Population3": "1,493,984"},
{"Name": "Raipur", "Status": "District", "Population1": "...", "Population2": "1,636,301", "Population3": "2,160,876"},
{"Name": "Rajnandgaon", "Status": "District", "Population1": "1,089,047", "Population2": "1,283,224", "Population3": "1,537,133"},
{"Name": "Sukma", "Status": " (", "Population1": ")", "Population2": "District", "Population3": "..."},
{"Name": "Surajpur", "Status": " (", "Population1": ")", "Population2": "District", "Population3": "..."},
{"Name": "Surguja", "Status": "District", "Population1": "...", "Population2": "712,959", "Population3": "840,352"},
{"Name": "Uttar Bastar Kanker", "Status": "District", "Population1": "548,000", "Population2": "650,934", "Population3": "748,941"},
{"Name": "Dadra & Nagar Haveli & Daman & Diu", "Status": "Union Territory", "Population1": "240,063", "Population2": "378,694", "Population3": "586,956"},
{"Name": "Dadra & Nagar Haveli", "Status": "District", "Population1": "138,477", "Population2": "220,490", "Population3": "343,709"},
{"Name": "Daman", "Status": "District", "Population1": "62,101", "Population2": "113,989", "Population3": "191,173"},
{"Name": "Diu", "Status": "District", "Population1": "39,485", "Population2": "44,215", "Population3": "52,074"},
{"Name": "Delhi", "Status": "Union Territory", "Population1": "9,420,644", "Population2": "13,850,507", "Population3": "16,787,941"},
{"Name": "Central", "Status": "District", "Population1": "656,533", "Population2": "646,385", "Population3": "582,320"},
{"Name": "East", "Status": "District", "Population1": "...", "Population2": "1,253,528", "Population3": "1,461,440"},
{"Name": "New Delhi", "Status": "District", "Population1": "168,669", "Population2": "179,112", "Population3": "142,004"},
{"Name": "North", "Status": "District", "Population1": "686,654", "Population2": "781,525", "Population3": "887,978"},
{"Name": "North East", "Status": "District", "Population1": "...", "Population2": "920,125", "Population3": "1,378,779"},
{"Name": "North West", "Status": "District", "Population1": "1,777,968", "Population2": "2,860,869", "Population3": "3,656,539"},
{"Name": "Shahdara", "Status": " (", "Population1": ")", "Population2": "District", "Population3": "..."},
{"Name": "South", "Status": "District", "Population1": "...", "Population2": "1,032,570", "Population3": "1,231,293"},
{"Name": "South East", "Status": " (", "Population1": ")", "Population2": "District", "Population3": "..."},
{"Name": "South West", "Status": "District", "Population1": "1,087,573", "Population2": "1,755,041", "Population3": "2,292,958"},
{"Name": "West", "Status": "District", "Population1": "1,433,038", "Population2": "2,128,908", "Population3": "2,543,243"},
{"Name": "Goa", "Status": "State", "Population1": "1,169,793", "Population2": "1,347,668", "Population3": "1,458,545"},
{"Name": "North Goa", "Status": "District", "Population1": "664,800", "Population2": "758,573", "Population3": "818,008"},
{"Name": "South Goa", "Status": "District", "Population1": "505,000", "Population2": "589,095", "Population3": "640,537"},
{"Name": "Gujarat", "Status": "State", "Population1": "41,309,582", "Population2": "50,671,017", "Population3": "60,439,692"},
{"Name": "Ahmadabad", "Status": "District", "Population1": "...", "Population2": "5,749,735", "Population3": "7,045,313"},
{"Name": "Amreli", "Status": "District", "Population1": "1,308,867", "Population2": "1,393,918", "Population3": "1,514,190"},
{"Name": "Anand", "Status": "District", "Population1": "1,642,615", "Population2": "1,856,872", "Population3": "2,092,745"},
{"Name": "Aravalli", "Status": " (", "Population1": ")", "Population2": "District", "Population3": "..."},
{"Name": "Banas Kantha", "Status": "District", "Population1": "1,981,513", "Population2": "2,504,244", "Population3": "3,120,506"},
{"Name": "Bharuch", "Status": "District", "Population1": "1,148,252", "Population2": "1,370,656", "Population3": "1,551,019"},
{"Name": "Bhavnagar", "Status": "District", "Population1": "...", "Population2": "2,065,492", "Population3": "2,393,272"},
{"Name": "Botad", "Status": " (", "Population1": ")", "Population2": "District", "Population3": "..."},
{"Name": "Chhota Udaipur", "Status": " (", "Population1": ")", "Population2": "District", "Population3": "..."},
{"Name": "Devbhumi Dwarka", "Status": " (", "Population1": ")", "Population2": "District", "Population3": "..."},
{"Name": "Dohad", "Status": "District", "Population1": "1,274,123", "Population2": "1,636,433", "Population3": "2,127,086"},
{"Name": "Gandhinagar", "Status": "District", "Population1": "1,016,300", "Population2": "1,237,168", "Population3": "1,391,753"},
{"Name": "Gir Somnath", "Status": " (", "Population1": ")", "Population2": "District", "Population3": "..."},
{"Name": "Jamnagar", "Status": "District", "Population1": "...", "Population2": "1,281,187", "Population3": "1,407,635"},
{"Name": "Junagadh", "Status": "District", "Population1": "...", "Population2": "1,388,498", "Population3": "1,525,605"},
{"Name": "Kachchh", "Status": "District", "Population1": "1,262,507", "Population2": "1,583,225", "Population3": "2,092,371"},
{"Name": "Kheda", "Status": "District", "Population1": "...", "Population2": "1,820,607", "Population3": "2,053,769"},
{"Name": "Mahesana", "Status": "District", "Population1": "1,646,000", "Population2": "1,844,856", "Population3": "2,035,064"},
{"Name": "Mahisagar", "Status": " (", "Population1": ")", "Population2": "District", "Population3": "..."},
{"Name": "Morbi", "Status": " (", "Population1": ")", "Population2": "District", "Population3": "..."},
{"Name": "Narmada", "Status": "District", "Population1": "449,376", "Population2": "514,404", "Population3": "590,297"},
{"Name": "Navsari", "Status": "District", "Population1": "1,085,692", "Population2": "1,229,463", "Population3": "1,329,672"},
{"Name": "Panch Mahals", "Status": "District", "Population1": "...", "Population2": "1,381,002", "Population3": "1,642,268"},
{"Name": "Patan", "Status": "District", "Population1": "1,036,019", "Population2": "1,182,709", "Population3": "1,343,734"},
{"Name": "Porbandar", "Status": "District", "Population1": "469,472", "Population2": "536,835", "Population3": "585,449"},
{"Name": "Rajkot", "Status": "District", "Population1": "...", "Population2": "2,488,885", "Population3": "3,015,229"},
{"Name": "Sabar Kantha", "Status": "District", "Population1": "...", "Population2": "1,173,734", "Population3": "1,388,671"},
{"Name": "Surat", "Status": "District", "Population1": "2,770,900", "Population2": "4,275,540", "Population3": "6,081,322"},
{"Name": "Surendranagar", "Status": "District", "Population1": "...", "Population2": "1,370,843", "Population3": "1,585,268"},
{"Name": "Tapi", "Status": "District", "Population1": "627,000", "Population2": "719,634", "Population3": "807,022"},
{"Name": "The Dangs", "Status": "District", "Population1": "144,091", "Population2": "186,729", "Population3": "228,291"},
{"Name": "Vadodara", "Status": "District", "Population1": "...", "Population2": "2,732,003", "Population3": "3,093,795"},
{"Name": "Valsad", "Status": "District", "Population1": "1,087,980", "Population2": "1,410,553", "Population3": "1,705,678"},
{"Name": "Haryana", "Status": "State", "Population1": "16,463,648", "Population2": "21,144,564", "Population3": "25,351,462"},
{"Name": "Ambala", "Status": "District", "Population1": "806,500", "Population2": "1,014,411", "Population3": "1,128,350"},
{"Name": "Bhiwani", "Status": "District", "Population1": "...", "Population2": "974,348", "Population3": "1,132,169"},
{"Name": "Charkhi Dadri", "Status": " (", "Population1": ")", "Population2": "District", "Population3": "..."},
{"Name": "Faridabad", "Status": "District", "Population1": "859,400", "Population2": "1,365,465", "Population3": "1,809,733"},
{"Name": "Fatehabad", "Status": "District", "Population1": "646,200", "Population2": "806,158", "Population3": "942,011"},
{"Name": "Gurgaon", "Status": "District", "Population1": "603,900", "Population2": "870,539", "Population3": "1,514,432"},
{"Name": "Hisar", "Status": "District", "Population1": "1,209,300", "Population2": "1,537,117", "Population3": "1,743,931"},
{"Name": "Jhajjar", "Status": "District", "Population1": "715,200", "Population2": "880,072", "Population3": "958,405"},
{"Name": "Jind", "Status": "District", "Population1": "980,400", "Population2": "1,189,827", "Population3": "1,334,152"},
{"Name": "Kaithal", "Status": "District", "Population1": "781,800", "Population2": "946,131", "Population3": "1,074,304"},
{"Name": "Karnal", "Status": "District", "Population1": "1,035,400", "Population2": "1,274,183", "Population3": "1,505,324"},
{"Name": "Kurukshetra", "Status": "District", "Population1": "669,400", "Population2": "825,454", "Population3": "964,655"},
{"Name": "Mahendragarh", "Status": "District", "Population1": "681,869", "Population2": "812,521", "Population3": "922,088"},
{"Name": "Mewat", "Status": "District", "Population1": "542,200", "Population2": "789,750", "Population3": "1,089,263"},
{"Name": "Palwal", "Status": "District", "Population1": "617,800", "Population2": "829,121", "Population3": "1,042,708"},
{"Name": "Panchkula", "Status": "District", "Population1": "310,400", "Population2": "468,411", "Population3": "561,293"},
{"Name": "Panipat", "Status": "District", "Population1": "698,100", "Population2": "967,449", "Population3": "1,205,437"},
{"Name": "Rewari", "Status": "District", "Population1": "610,600", "Population2": "765,351", "Population3": "900,332"},
{"Name": "Rohtak", "Status": "District", "Population1": "777,000", "Population2": "940,128", "Population3": "1,061,204"},
{"Name": "Sirsa", "Status": "District", "Population1": "903,536", "Population2": "1,116,649", "Population3": "1,295,189"},
{"Name": "Sonipat", "Status": "District", "Population1": "1,045,200", "Population2": "1,279,175", "Population3": "1,450,001"},
{"Name": "Yamunanagar", "Status": "District", "Population1": "806,300", "Population2": "1,041,630", "Population3": "1,214,205"},
{"Name": "Himachal Pradesh", "Status": "State", "Population1": "5,170,877", "Population2": "6,077,900", "Population3": "6,864,602"},
{"Name": "Bilaspur", "Status": "District", "Population1": "295,387", "Population2": "340,885", "Population3": "381,956"},
{"Name": "Chamba", "Status": "District", "Population1": "393,286", "Population2": "460,887", "Population3": "519,080"},
{"Name": "Hamirpur", "Status": "District", "Population1": "369,128", "Population2": "412,700", "Population3": "454,768"},
{"Name": "Kangra", "Status": "District", "Population1": "1,174,072", "Population2": "1,339,030", "Population3": "1,510,075"},
{"Name": "Kinnaur", "Status": "District", "Population1": "71,270", "Population2": "78,334", "Population3": "84,121"},
{"Name": "Kullu", "Status": "District", "Population1": "302,432", "Population2": "381,571", "Population3": "437,903"},
{"Name": "Lahul & Spiti", "Status": "District", "Population1": "31,294", "Population2": "33,224", "Population3": "31,564"},
{"Name": "Mandi", "Status": "District", "Population1": "776,372", "Population2": "901,344", "Population3": "999,777"},
{"Name": "Shimla", "Status": "District", "Population1": "617,404", "Population2": "722,502", "Population3": "814,010"},
{"Name": "Sirmaur", "Status": "District", "Population1": "379,695", "Population2": "458,593", "Population3": "529,855"},
{"Name": "Solan", "Status": "District", "Population1": "382,268", "Population2": "500,557", "Population3": "580,320"},
{"Name": "Una", "Status": "District", "Population1": "378,269", "Population2": "448,273", "Population3": "521,173"},
{"Name": "Jammu & Kashmir", "Status": "Union Territory", "Population1": "7,656,000", "Population2": "9,907,161", "Population3": "12,267,013"},
{"Name": "Anantnag", "Status": "District", "Population1": "586,300", "Population2": "778,408", "Population3": "1,078,692"},
{"Name": "Badgam", "Status": "District", "Population1": "466,700", "Population2": "607,181", "Population3": "753,745"},
{"Name": "Bandipore", "Status": "District", "Population1": "232,200", "Population2": "304,886", "Population3": "392,232"},
{"Name": "Baramula", "Status": "District", "Population1": "642,800", "Population2": "843,892", "Population3": "1,008,039"},
{"Name": "Doda", "Status": "District", "Population1": "252,500", "Population2": "320,256", "Population3": "409,936"},
{"Name": "Ganderbal", "Status": "District", "Population1": "168,200", "Population2": "217,907", "Population3": "297,446"},
{"Name": "Jammu", "Status": "District", "Population1": "1,051,900", "Population2": "1,357,077", "Population3": "1,529,958"},
{"Name": "Kathua", "Status": "District", "Population1": "421,000", "Population2": "511,455", "Population3": "616,435"},
{"Name": "Kishtwar", "Status": "District", "Population1": "150,500", "Population2": "190,843", "Population3": "230,696"},
{"Name": "Kulgam", "Status": "District", "Population1": "296,800", "Population2": "394,026", "Population3": "424,483"},
{"Name": "Kupwara", "Status": "District", "Population1": "466,000", "Population2": "650,393", "Population3": "870,354"},
{"Name": "Pulwama", "Status": "District", "Population1": "349,100", "Population2": "441,275", "Population3": "560,440"},
{"Name": "Punch", "Status": "District", "Population1": "290,700", "Population2": "372,613", "Population3": "476,835"},
{"Name": "Rajouri", "Status": "District", "Population1": "384,400", "Population2": "483,284", "Population3": "642,415"},
{"Name": "Ramban", "Status": "District", "Population1": "169,400", "Population2": "214,944", "Population3": "283,713"},
{"Name": "Reasi", "Status": "District", "Population1": "194,600", "Population2": "247,694", "Population3": "314,667"},
{"Name": "Samba", "Status": "District", "Population1": "211,300", "Population2": "272,539", "Population3": "318,898"},
{"Name": "Shupiyan", "Status": "District", "Population1": "167,200", "Population2": "211,332", "Population3": "266,215"},
{"Name": "Srinagar", "Status": "District", "Population1": "793,500", "Population2": "1,027,670", "Population3": "1,236,829"},
{"Name": "Udhampur", "Status": "District", "Population1": "360,900", "Population2": "459,486", "Population3": "554,985"},
{"Name": "Jharkhand", "Status": "State", "Population1": "21,843,911", "Population2": "26,945,829", "Population3": "32,988,134"},
{"Name": "Bokaro", "Status": "District", "Population1": "...", "Population2": "1,777,662", "Population3": "2,062,330"},
{"Name": "Chatra", "Status": "District", "Population1": "...", "Population2": "808,135", "Population3": "1,042,886"},
{"Name": "Deoghar", "Status": "District", "Population1": "933,113", "Population2": "1,165,390", "Population3": "1,492,073"},
{"Name": "Dhanbad", "Status": "District", "Population1": "1,949,526", "Population2": "2,397,102", "Population3": "2,684,487"},
{"Name": "Dumka", "Status": "District", "Population1": "...", "Population2": "1,106,521", "Population3": "1,321,442"},
{"Name": "Garhwa", "Status": "District", "Population1": "801,350", "Population2": "1,035,464", "Population3": "1,322,784"},
{"Name": "Giridih", "Status": "District", "Population1": "1,496,200", "Population2": "1,905,343", "Population3": "2,445,474"},
{"Name": "Godda", "Status": "District", "Population1": "861,182", "Population2": "1,047,939", "Population3": "1,313,551"},
{"Name": "Gumla", "Status": "District", "Population1": "...", "Population2": "832,447", "Population3": "1,025,213"},
{"Name": "Hazaribagh", "Status": "District", "Population1": "...", "Population2": "1,378,881", "Population3": "1,734,495"},
{"Name": "Jamtara", "Status": "District", "Population1": "...", "Population2": "653,081", "Population3": "791,042"},
{"Name": "Khunti", "Status": "District", "Population1": "...", "Population2": "434,819", "Population3": "531,885"},
{"Name": "Kodarma", "Status": "District", "Population1": "...", "Population2": "540,901", "Population3": "716,259"},
{"Name": "Latehar", "Status": "District", "Population1": "...", "Population2": "560,894", "Population3": "726,978"},
{"Name": "Lohardaga", "Status": "District", "Population1": "288,886", "Population2": "364,521", "Population3": "461,790"},
{"Name": "Pakur", "Status": "District", "Population1": "564,253", "Population2": "701,664", "Population3": "900,422"},
{"Name": "Palamu", "Status": "District", "Population1": "...", "Population2": "1,537,465", "Population3": "1,939,869"},
{"Name": "Pashchimi Singhbhum", "Status": "District", "Population1": "...", "Population2": "1,233,945", "Population3": "1,502,338"},
{"Name": "Purbi Singhbhum", "Status": "District", "Population1": "1,613,088", "Population2": "1,982,988", "Population3": "2,293,919"},
{"Name": "Ramgarh", "Status": "District", "Population1": "...", "Population2": "839,482", "Population3": "949,443"},
{"Name": "Ranchi", "Status": "District", "Population1": "...", "Population2": "2,350,245", "Population3": "2,914,253"},
{"Name": "Sahibganj", "Status": "District", "Population1": "736,835", "Population2": "927,770", "Population3": "1,150,567"},
{"Name": "Saraikela-kharsawan", "Status": "District", "Population1": "...", "Population2": "848,850", "Population3": "1,065,056"},
{"Name": "Simdega", "Status": "District", "Population1": "...", "Population2": "514,320", "Population3": "599,578"},
{"Name": "Karnataka", "Status": "State", "Population1": "44,977,201", "Population2": "52,850,562", "Population3": "61,095,297"},
{"Name": "Bagalkot", "Status": "District", "Population1": "1,390,259", "Population2": "1,651,892", "Population3": "1,889,752"},
{"Name": "Bangalore", "Status": "District", "Population1": "4,839,162", "Population2": "6,537,124", "Population3": "9,621,551"},
{"Name": "Bangalore Rural", "Status": "District", "Population1": "717,525", "Population2": "850,968", "Population3": "990,923"},
{"Name": "Belgaum", "Status": "District", "Population1": "3,583,606", "Population2": "4,214,505", "Population3": "4,779,661"},
{"Name": "Bellary", "Status": "District", "Population1": "1,656,000", "Population2": "2,027,140", "Population3": "2,452,595"},
{"Name": "Bidar", "Status": "District", "Population1": "1,255,799", "Population2": "1,502,373", "Population3": "1,703,300"},
{"Name": "Bijapur", "Status": "District", "Population1": "1,537,731", "Population2": "1,806,918", "Population3": "2,177,331"},
{"Name": "Chamarajanagar", "Status": "District", "Population1": "883,365", "Population2": "965,462", "Population3": "1,020,791"},
{"Name": "Chikkaballapura", "Status": "District", "Population1": "1,005,031", "Population2": "1,149,007", "Population3": "1,255,104"},
{"Name": "Chikmagalur", "Status": "District", "Population1": "1,017,283", "Population2": "1,140,905", "Population3": "1,137,961"},
{"Name": "Chitradurga", "Status": "District", "Population1": "1,312,717", "Population2": "1,517,896", "Population3": "1,659,456"},
{"Name": "Dakshina Kannada", "Status": "District", "Population1": "1,656,165", "Population2": "1,897,730", "Population3": "2,089,649"},
{"Name": "Davanagere", "Status": "District", "Population1": "1,559,222", "Population2": "1,790,952", "Population3": "1,945,497"},
{"Name": "Dharwad", "Status": "District", "Population1": "1,374,895", "Population2": "1,604,253", "Population3": "1,847,023"},
{"Name": "Gadag", "Status": "District", "Population1": "859,042", "Population2": "971,835", "Population3": "1,064,570"},
{"Name": "Gulbarga", "Status": "District", "Population1": "1,786,138", "Population2": "2,174,742", "Population3": "2,566,326"},
{"Name": "Hassan", "Status": "District", "Population1": "1,569,684", "Population2": "1,721,669", "Population3": "1,776,421"},
{"Name": "Haveri", "Status": "District", "Population1": "1,269,213", "Population2": "1,439,116", "Population3": "1,597,668"},
{"Name": "Kodagu", "Status": "District", "Population1": "488,455", "Population2": "548,561", "Population3": "554,519"},
{"Name": "Kolar", "Status": "District", "Population1": "1,211,858", "Population2": "1,387,062", "Population3": "1,536,401"},
{"Name": "Koppal", "Status": "District", "Population1": "958,078", "Population2": "1,196,089", "Population3": "1,389,920"},
{"Name": "Mandya", "Status": "District", "Population1": "1,644,374", "Population2": "1,763,705", "Population3": "1,805,769"},
{"Name": "Mysore", "Status": "District", "Population1": "2,281,653", "Population2": "2,641,027", "Population3": "3,001,127"},
{"Name": "Raichur", "Status": "District", "Population1": "1,351,809", "Population2": "1,669,762", "Population3": "1,928,812"},
{"Name": "Ramanagara", "Status": "District", "Population1": "955,669", "Population2": "1,030,546", "Population3": "1,082,636"},
{"Name": "Shimoga", "Status": "District", "Population1": "1,452,259", "Population2": "1,642,545", "Population3": "1,752,753"},
{"Name": "Tumkur", "Status": "District", "Population1": "2,305,819", "Population2": "2,584,711", "Population3": "2,678,980"},
{"Name": "Udupi", "Status": "District", "Population1": "1,038,099", "Population2": "1,112,243", "Population3": "1,177,361"},
{"Name": "Uttara Kannada", "Status": "District", "Population1": "1,220,260", "Population2": "1,353,644", "Population3": "1,437,169"},
{"Name": "Yadgir", "Status": "District", "Population1": "796,031", "Population2": "956,180", "Population3": "1,174,271"},
{"Name": "Kerala", "Status": "State", "Population1": "29,098,518", "Population2": "31,841,374", "Population3": "33,406,061"},
{"Name": "Alappuzha", "Status": "District", "Population1": "2,001,217", "Population2": "2,109,160", "Population3": "2,127,789"},
{"Name": "Ernakulam", "Status": "District", "Population1": "2,840,200", "Population2": "3,105,798", "Population3": "3,282,388"},
{"Name": "Idukki", "Status": "District", "Population1": "1,055,100", "Population2": "1,129,221", "Population3": "1,108,974"},
{"Name": "Kannur", "Status": "District", "Population1": "2,251,727", "Population2": "2,408,956", "Population3": "2,523,003"},
{"Name": "Kasaragod", "Status": "District", "Population1": "1,071,508", "Population2": "1,204,078", "Population3": "1,307,375"},
{"Name": "Kollam", "Status": "District", "Population1": "2,407,566", "Population2": "2,585,208", "Population3": "2,635,375"},
{"Name": "Kottayam", "Status": "District", "Population1": "1,828,271", "Population2": "1,953,646", "Population3": "1,974,551"},
{"Name": "Kozhikode", "Status": "District", "Population1": "2,619,914", "Population2": "2,879,131", "Population3": "3,086,293"},
{"Name": "Malappuram", "Status": "District", "Population1": "3,096,330", "Population2": "3,625,471", "Population3": "4,112,920"},
{"Name": "Palakkad", "Status": "District", "Population1": "2,382,235", "Population2": "2,617,482", "Population3": "2,809,934"},
{"Name": "Pathanamthitta", "Status": "District", "Population1": "1,188,352", "Population2": "1,234,016", "Population3": "1,197,412"},
{"Name": "Thiruvananthapuram", "Status": "District", "Population1": "2,946,650", "Population2": "3,234,356", "Population3": "3,301,427"},
{"Name": "Thrissur", "Status": "District", "Population1": "2,737,311", "Population2": "2,974,232", "Population3": "3,121,200"},
{"Name": "Wayanad", "Status": "District", "Population1": "672,128", "Population2": "780,619", "Population3": "817,420"},
{"Name": "Ladakh", "Status": "Union Territory", "Population1": "179,400", "Population2": "236,539", "Population3": "274,289"},
{"Name": "Kargil", "Status": "District", "Population1": "89,300", "Population2": "119,307", "Population3": "140,802"},
{"Name": "Leh", "Status": "District", "Population1": "90,100", "Population2": "117,232", "Population3": "133,487"},
{"Name": "Lakshadweep", "Status": "Union Territory", "Population1": "51,707", "Population2": "60,650", "Population3": "64,473"},
{"Name": "Lakshadweep", "Status": "Union Territory", "Population1": "51,681", "Population2": "60,650", "Population3": "64,473"},
{"Name": "Madhya Pradesh", "Status": "State", "Population1": "48,566,242", "Population2": "60,348,023", "Population3": "72,626,809"},
{"Name": "Agar Malwa", "Status": " (", "Population1": ")", "Population2": "District", "Population3": "..."},
{"Name": "Alirajpur", "Status": "District", "Population1": "483,481", "Population2": "610,275", "Population3": "728,999"},
{"Name": "Anuppur", "Status": "District", "Population1": "556,074", "Population2": "667,155", "Population3": "749,237"},
{"Name": "Ashoknagar", "Status": "District", "Population1": "559,257", "Population2": "688,940", "Population3": "845,071"},
{"Name": "Balaghat", "Status": "District", "Population1": "1,365,870", "Population2": "1,497,968", "Population3": "1,701,698"},
{"Name": "Barwani", "Status": "District", "Population1": "835,625", "Population2": "1,086,366", "Population3": "1,385,881"},
{"Name": "Betul", "Status": "District", "Population1": "1,181,501", "Population2": "1,395,175", "Population3": "1,575,362"},
{"Name": "Bhind", "Status": "District", "Population1": "1,219,000", "Population2": "1,428,559", "Population3": "1,703,005"},
{"Name": "Bhopal", "Status": "District", "Population1": "1,351,479", "Population2": "1,843,510", "Population3": "2,371,061"},
{"Name": "Burhanpur", "Status": "District", "Population1": "533,066", "Population2": "634,883", "Population3": "757,847"},
{"Name": "Chhatarpur", "Status": "District", "Population1": "1,158,076", "Population2": "1,474,723", "Population3": "1,762,375"},
{"Name": "Chhindwara", "Status": "District", "Population1": "1,568,702", "Population2": "1,849,283", "Population3": "2,090,922"},
{"Name": "Damoh", "Status": "District", "Population1": "898,125", "Population2": "1,083,949", "Population3": "1,264,219"},
{"Name": "Datia", "Status": "District", "Population1": "544,547", "Population2": "664,159", "Population3": "786,754"},
{"Name": "Dewas", "Status": "District", "Population1": "1,033,807", "Population2": "1,308,223", "Population3": "1,563,715"},
{"Name": "Dhar", "Status": "District", "Population1": "1,367,412", "Population2": "1,740,329", "Population3": "2,185,793"},
{"Name": "Dindori", "Status": "District", "Population1": "511,849", "Population2": "580,730", "Population3": "704,524"},
{"Name": "Guna", "Status": "District", "Population1": "751,060", "Population2": "977,827", "Population3": "1,241,519"},
{"Name": "Gwalior", "Status": "District", "Population1": "1,293,567", "Population2": "1,632,109", "Population3": "2,032,036"},
{"Name": "Harda", "Status": "District", "Population1": "380,762", "Population2": "474,416", "Population3": "570,465"},
{"Name": "Hoshangabad", "Status": "District", "Population1": "886,449", "Population2": "1,084,265", "Population3": "1,241,350"},
{"Name": "Indore", "Status": "District", "Population1": "1,835,915", "Population2": "2,465,827", "Population3": "3,276,697"},
{"Name": "Jabalpur", "Status": "District", "Population1": "1,768,037", "Population2": "2,151,203", "Population3": "2,463,289"},
{"Name": "Jhabua", "Status": "District", "Population1": "646,924", "Population2": "784,286", "Population3": "1,025,048"},
{"Name": "Katni", "Status": "District", "Population1": "881,925", "Population2": "1,064,167", "Population3": "1,292,042"},
{"Name": "Khandwa", "Status": " (", "Population1": ")", "Population2": "District", "Population3": "898,596"},
{"Name": "Khargone", "Status": " (", "Population1": ")", "Population2": "District", "Population3": "1,192,520"},
{"Name": "Mandla", "Status": "District", "Population1": "779,414", "Population2": "894,236", "Population3": "1,054,905"},
{"Name": "Mandsaur", "Status": "District", "Population1": "956,869", "Population2": "1,183,724", "Population3": "1,340,411"},
{"Name": "Morena", "Status": "District", "Population1": "1,279,094", "Population2": "1,592,714", "Population3": "1,965,970"},
{"Name": "Narsimhapur", "Status": "District", "Population1": "785,496", "Population2": "957,646", "Population3": "1,091,854"},
{"Name": "Neemuch", "Status": "District", "Population1": "598,339", "Population2": "726,070", "Population3": "826,067"},
{"Name": "Panna", "Status": "District", "Population1": "687,945", "Population2": "856,558", "Population3": "1,016,520"},
{"Name": "Raisen", "Status": "District", "Population1": "876,461", "Population2": "1,125,154", "Population3": "1,331,597"},
{"Name": "Rajgarh", "Status": "District", "Population1": "992,764", "Population2": "1,254,085", "Population3": "1,545,814"},
{"Name": "Ratlam", "Status": "District", "Population1": "971,888", "Population2": "1,215,393", "Population3": "1,455,069"},
{"Name": "Rewa", "Status": "District", "Population1": "1,554,987", "Population2": "1,973,306", "Population3": "2,365,106"},
{"Name": "Sagar", "Status": "District", "Population1": "1,647,736", "Population2": "2,021,987", "Population3": "2,378,458"},
{"Name": "Satna", "Status": "District", "Population1": "1,465,384", "Population2": "1,870,104", "Population3": "2,228,935"},
{"Name": "Sehore", "Status": "District", "Population1": "841,358", "Population2": "1,078,912", "Population3": "1,311,332"},
{"Name": "Seoni", "Status": "District", "Population1": "1,000,831", "Population2": "1,166,608", "Population3": "1,379,131"},
{"Name": "Shahdol", "Status": "District", "Population1": "766,980", "Population2": "908,148", "Population3": "1,066,063"},
{"Name": "Shajapur", "Status": "District", "Population1": "...", "Population2": "810,322", "Population3": "941,403"},
{"Name": "Sheopur", "Status": "District", "Population1": "431,480", "Population2": "559,495", "Population3": "687,861"},
{"Name": "Shivpuri", "Status": "District", "Population1": "1,103,790", "Population2": "1,406,031", "Population3": "1,726,050"},
{"Name": "Sidhi", "Status": "District", "Population1": "709,436", "Population2": "910,983", "Population3": "1,127,033"},
{"Name": "Singrauli", "Status": "District", "Population1": "663,998", "Population2": "920,169", "Population3": "1,178,273"},
{"Name": "Tikamgarh", "Status": "District", "Population1": "940,829", "Population2": "1,202,998", "Population3": "1,445,166"},
{"Name": "Ujjain", "Status": "District", "Population1": "1,383,086", "Population2": "1,710,982", "Population3": "1,986,864"},
{"Name": "Umaria", "Status": "District", "Population1": "420,815", "Population2": "515,963", "Population3": "644,758"},
{"Name": "Vidisha", "Status": "District", "Population1": "970,388", "Population2": "1,214,857", "Population3": "1,458,875"},
{"Name": "Maharashtra", "Status": "State", "Population1": "78,937,187", "Population2": "96,878,627", "Population3": "112,374,333"},
{"Name": "Ahmadnagar", "Status": "District", "Population1": "3,372,935", "Population2": "4,040,642", "Population3": "4,543,159"},
{"Name": "Akola", "Status": "District", "Population1": "1,351,495", "Population2": "1,629,633", "Population3": "1,813,906"},
{"Name": "Amravati", "Status": "District", "Population1": "2,200,057", "Population2": "2,607,160", "Population3": "2,888,445"},
{"Name": "Aurangabad", "Status": "District", "Population1": "2,218,606", "Population2": "2,902,602", "Population3": "3,701,282"},
{"Name": "Bhandara", "Status": "District", "Population1": "1,021,408", "Population2": "1,136,146", "Population3": "1,200,334"},
{"Name": "Bid", "Status": "District", "Population1": "1,822,072", "Population2": "2,161,250", "Population3": "2,585,049"},
{"Name": "Buldana", "Status": "District", "Population1": "1,886,299", "Population2": "2,232,480", "Population3": "2,586,258"},
{"Name": "Chandrapur", "Status": "District", "Population1": "1,771,994", "Population2": "2,071,101", "Population3": "2,204,307"},
{"Name": "Dhule", "Status": "District", "Population1": "1,473,170", "Population2": "1,707,947", "Population3": "2,050,862"},
{"Name": "Gadchiroli", "Status": "District", "Population1": "787,010", "Population2": "970,294", "Population3": "1,072,942"},
{"Name": "Gondiya", "Status": "District", "Population1": "1,086,221", "Population2": "1,200,707", "Population3": "1,322,507"},
{"Name": "Hingoli", "Status": "District", "Population1": "823,931", "Population2": "987,160", "Population3": "1,177,345"},
{"Name": "Jalgaon", "Status": "District", "Population1": "3,187,634", "Population2": "3,682,690", "Population3": "4,229,917"},
{"Name": "Jalna", "Status": "District", "Population1": "1,359,546", "Population2": "1,607,391", "Population3": "1,959,046"},
{"Name": "Kolhapur", "Status": "District", "Population1": "2,989,507", "Population2": "3,523,162", "Population3": "3,876,001"},
{"Name": "Latur", "Status": "District", "Population1": "1,676,641", "Population2": "2,080,285", "Population3": "2,454,196"},
{"Name": "Mumbai", "Status": "District", "Population1": "3,174,889", "Population2": "3,338,031", "Population3": "3,085,411"},
{"Name": "Mumbai Suburban", "Status": "District", "Population1": "6,751,002", "Population2": "8,640,419", "Population3": "9,356,962"},
{"Name": "Nagpur", "Status": "District", "Population1": "3,287,139", "Population2": "4,067,637", "Population3": "4,653,570"},
{"Name": "Nanded", "Status": "District", "Population1": "2,330,374", "Population2": "2,876,259", "Population3": "3,361,292"},
{"Name": "Nandurbar", "Status": "District", "Population1": "1,062,545", "Population2": "1,311,709", "Population3": "1,648,295"},
{"Name": "Nashik", "Status": "District", "Population1": "3,851,352", "Population2": "4,993,796", "Population3": "6,107,187"},
{"Name": "Osmanabad", "Status": "District", "Population1": "1,276,327", "Population2": "1,486,586", "Population3": "1,657,576"},
{"Name": "Palghar", "Status": " (", "Population1": ")", "Population2": "District", "Population3": "..."},
{"Name": "Parbhani", "Status": "District", "Population1": "1,293,104", "Population2": "1,527,715", "Population3": "1,836,086"},
{"Name": "Pune", "Status": "District", "Population1": "5,532,532", "Population2": "7,232,555", "Population3": "9,429,408"},
{"Name": "Raigad", "Status": " (", "Population1": ")", "Population2": "District", "Population3": "1,824,816"},
{"Name": "Ratnagiri", "Status": "District", "Population1": "1,544,057", "Population2": "1,696,777", "Population3": "1,615,069"},
{"Name": "Sangli", "Status": "District", "Population1": "2,209,488", "Population2": "2,583,524", "Population3": "2,822,143"},
{"Name": "Satara", "Status": "District", "Population1": "2,451,372", "Population2": "2,808,994", "Population3": "3,003,741"},
{"Name": "Sindhudurg", "Status": "District", "Population1": "832,152", "Population2": "868,825", "Population3": "849,651"},
{"Name": "Solapur", "Status": "District", "Population1": "3,231,057", "Population2": "3,849,543", "Population3": "4,317,756"},
{"Name": "Thane", "Status": "District", "Population1": "...", "Population2": "5,992,940", "Population3": "8,070,032"},
{"Name": "Wardha", "Status": "District", "Population1": "1,067,357", "Population2": "1,236,736", "Population3": "1,300,774"},
{"Name": "Washim", "Status": "District", "Population1": "862,764", "Population2": "1,020,822", "Population3": "1,197,160"},
{"Name": "Yavatmal", "Status": "District", "Population1": "2,077,144", "Population2": "2,458,271", "Population3": "2,772,348"},
{"Name": "Manipur", "Status": "State", "Population1": "1,837,149", "Population2": "2,293,896", "Population3": "2,855,794"},
{"Name": "Bishnupur", "Status": "District", "Population1": "180,773", "Population2": "208,368", "Population3": "237,399"},
{"Name": "Chandel", "Status": "District", "Population1": "...", "Population2": "69,478", "Population3": "85,072"},
{"Name": "Churachandpur", "Status": "District", "Population1": "...", "Population2": "180,439", "Population3": "226,884"},
{"Name": "Imphal East", "Status": "District", "Population1": "...", "Population2": "357,048", "Population3": "412,275"},
{"Name": "Imphal West", "Status": "District", "Population1": "380,801", "Population2": "444,382", "Population3": "517,992"},
{"Name": "Jiribam", "Status": " (", "Population1": ")", "Population2": "District", "Population3": "..."},
{"Name": "Kakching", "Status": " (", "Population1": ")", "Population2": "District", "Population3": "..."},
{"Name": "Kamjong", "Status": " (", "Population1": ")", "Population2": "District", "Population3": "..."},
{"Name": "Kangpokpi", "Status": " (", "Population1": ")", "Population2": "District", "Population3": "..."},
{"Name": "Noney", "Status": " (", "Population1": ")", "Population2": "District", "Population3": "..."},
{"Name": "Pherzawl", "Status": " (", "Population1": ")", "Population2": "District", "Population3": "..."},
{"Name": "Senapati", "Status": "District", "Population1": "...", "Population2": "...", "Population3": "285,404"},
{"Name": "Tamenglong", "Status": "District", "Population1": "...", "Population2": "80,762", "Population3": "103,980"},
{"Name": "Tengnoupal", "Status": " (", "Population1": ")", "Population2": "District", "Population3": "..."},
{"Name": "Thoubal", "Status": "District", "Population1": "...", "Population2": "245,286", "Population3": "286,687"},
{"Name": "Ukhrul", "Status": "District", "Population1": "...", "Population2": "104,342", "Population3": "138,382"},
{"Name": "Meghalaya", "Status": "State", "Population1": "1,774,778", "Population2": "2,318,822", "Population3": "2,966,889"},
{"Name": "East Garo Hills", "Status": "District", "Population1": "...", "Population2": "103,000", "Population3": "132,300"},
{"Name": "East Jaintia Hills", "Status": " (", "Population1": ")", "Population2": "District", "Population3": "..."},
{"Name": "East Khasi Hills", "Status": "District", "Population1": "535,600", "Population2": "660,923", "Population3": "825,922"},
{"Name": "North Garo Hills", "Status": " (", "Population1": ")", "Population2": "District", "Population3": "..."},
{"Name": "Ribhoi", "Status": "District", "Population1": "127,312", "Population2": "192,790", "Population3": "258,840"},
{"Name": "South Garo Hills", "Status": "District", "Population1": "83,300", "Population2": "110,244", "Population3": "142,334"},
{"Name": "South West Garo Hills", "Status": " (", "Population1": ")", "Population2": "District", "Population3": "..."},
{"Name": "South West Khasi Hills", "Status": " (", "Population1": ")", "Population2": "District", "Population3": "..."},
{"Name": "West Garo Hills", "Status": "District", "Population1": "...", "Population2": "405,000", "Population3": "518,400"},
{"Name": "West Jaintia Hills", "Status": " (", "Population1": ")", "Population2": "District", "Population3": "..."},
{"Name": "West Khasi Hills", "Status": "District", "Population1": "...", "Population2": "227,000", "Population3": "294,100"},
{"Name": "Mizoram", "Status": "State", "Population1": "689,756", "Population2": "888,573", "Population3": "1,097,206"},
{"Name": "Aizawl", "Status": "District", "Population1": "235,900", "Population2": "325,676", "Population3": "400,309"},
{"Name": "Champhai", "Status": "District", "Population1": "83,000", "Population2": "107,793", "Population3": "125,745"},
{"Name": "Kolasib", "Status": "District", "Population1": "48,800", "Population2": "65,960", "Population3": "83,955"},
{"Name": "Lawngtlai", "Status": "District", "Population1": "64,900", "Population2": "87,592", "Population3": "117,894"},
{"Name": "Lunglei", "Status": "District", "Population1": "111,415", "Population2": "137,223", "Population3": "161,428"},
{"Name": "Mamit", "Status": "District", "Population1": "64,600", "Population2": "62,785", "Population3": "86,364"},
{"Name": "Saiha", "Status": "District", "Population1": "34,900", "Population2": "47,084", "Population3": "56,574"},
{"Name": "Serchhip", "Status": "District", "Population1": "46,200", "Population2": "54,460", "Population3": "64,937"},
{"Name": "Nagaland", "Status": "State", "Population1": "1,209,546", "Population2": "1,990,036", "Population3": "1,978,502"},
{"Name": "Dimapur", "Status": "District", "Population1": "...", "Population2": "308,429", "Population3": "378,811"},
{"Name": "Kiphire", "Status": "District", "Population1": "...", "Population2": "106,591", "Population3": "74,004"},
{"Name": "Kohima", "Status": "District", "Population1": "...", "Population2": "219,913", "Population3": "267,988"},
{"Name": "Longleng", "Status": "District", "Population1": "...", "Population2": "121,581", "Population3": "50,484"},
{"Name": "Mokokchung", "Status": "District", "Population1": "158,374", "Population2": "232,085", "Population3": "194,622"},
{"Name": "Mon", "Status": "District", "Population1": "149,699", "Population2": "260,652", "Population3": "250,260"},
{"Name": "Peren", "Status": "District", "Population1": "...", "Population2": "90,766", "Population3": "95,219"},
{"Name": "Phek", "Status": "District", "Population1": "102,156", "Population2": "148,195", "Population3": "163,418"},
{"Name": "Tuensang", "Status": "District", "Population1": "...", "Population2": "186,003", "Population3": "196,596"},
{"Name": "Wokha", "Status": "District", "Population1": "82,612", "Population2": "161,223", "Population3": "166,343"},
{"Name": "Zunheboto", "Status": "District", "Population1": "96,218", "Population2": "154,598", "Population3": "140,757"},
{"Name": "Odisha", "Status": " (", "Population1": ")", "Population2": "State", "Population3": "31,659,736"},
{"Name": "Anugul", "Status": "District", "Population1": "961,037", "Population2": "1,140,003", "Population3": "1,273,821"},
{"Name": "Balangir", "Status": "District", "Population1": "1,230,938", "Population2": "1,337,194", "Population3": "1,648,997"},
{"Name": "Baleshwar", "Status": "District", "Population1": "1,696,583", "Population2": "2,024,508", "Population3": "2,320,529"},
{"Name": "Bargarh", "Status": "District", "Population1": "1,207,172", "Population2": "1,346,336", "Population3": "1,481,255"},
{"Name": "Baudh", "Status": "District", "Population1": "317,622", "Population2": "373,372", "Population3": "441,162"},
{"Name": "Bhadrak", "Status": "District", "Population1": "1,105,834", "Population2": "1,333,749", "Population3": "1,506,337"},
{"Name": "Cuttack", "Status": "District", "Population1": "2,053,000", "Population2": "2,340,832", "Population3": "2,624,470"},
{"Name": "Debagarh", "Status": "District", "Population1": "234,238", "Population2": "274,108", "Population3": "312,520"},
{"Name": "Dhenkanal", "Status": "District", "Population1": "947,870", "Population2": "1,066,878", "Population3": "1,192,811"},
{"Name": "Gajapati", "Status": "District", "Population1": "454,708", "Population2": "518,837", "Population3": "577,817"},
{"Name": "Ganjam", "Status": "District", "Population1": "2,704,056", "Population2": "3,160,635", "Population3": "3,529,031"},
{"Name": "Jagatsinghapur", "Status": "District", "Population1": "934,000", "Population2": "1,057,891", "Population3": "1,136,971"},
{"Name": "Jajapur", "Status": "District", "Population1": "1,386,177", "Population2": "1,624,341", "Population3": "1,827,192"},
{"Name": "Jharsuguda", "Status": "District", "Population1": "446,700", "Population2": "514,853", "Population3": "579,505"},
{"Name": "Kalahandi", "Status": "District", "Population1": "1,130,903", "Population2": "1,335,494", "Population3": "1,576,869"},
{"Name": "Kandhamal", "Status": "District", "Population1": "546,281", "Population2": "648,201", "Population3": "733,110"},
{"Name": "Kendrapara", "Status": "District", "Population1": "1,149,501", "Population2": "1,302,005", "Population3": "1,440,361"},
{"Name": "Kendujhar", "Status": "District", "Population1": "1,337,026", "Population2": "1,561,990", "Population3": "1,801,733"},
{"Name": "Khordha", "Status": "District", "Population1": "1,502,014", "Population2": "1,877,395", "Population3": "2,251,673"},
{"Name": "Koraput", "Status": "District", "Population1": "1,029,600", "Population2": "1,180,637", "Population3": "1,379,647"},
{"Name": "Malkangiri", "Status": "District", "Population1": "422,300", "Population2": "504,198", "Population3": "613,192"},
{"Name": "Mayurbhanj", "Status": "District", "Population1": "1,884,580", "Population2": "2,223,456", "Population3": "2,519,738"},
{"Name": "Nabarangapur", "Status": "District", "Population1": "846,700", "Population2": "1,025,766", "Population3": "1,220,946"},
{"Name": "Nayagarh", "Status": "District", "Population1": "782,647", "Population2": "864,516", "Population3": "962,789"},
{"Name": "Nuapada", "Status": "District", "Population1": "469,482", "Population2": "530,690", "Population3": "610,382"},
{"Name": "Puri", "Status": "District", "Population1": "1,305,365", "Population2": "1,502,682", "Population3": "1,698,730"},
{"Name": "Rayagada", "Status": "District", "Population1": "713,984", "Population2": "831,109", "Population3": "967,911"},
{"Name": "Sambalpur", "Status": "District", "Population1": "809,000", "Population2": "930,476", "Population3": "1,041,099"},
{"Name": "Subarnapur", "Status": "District", "Population1": "476,815", "Population2": "541,835", "Population3": "610,183"},
{"Name": "Sundargarh", "Status": "District", "Population1": "1,573,617", "Population2": "1,830,673", "Population3": "2,093,437"},
{"Name": "Puducherry", "Status": " (", "Population1": ")", "Population2": "Union Territory", "Population3": "807,785"},
{"Name": "Karaikal", "Status": "District", "Population1": "145,703", "Population2": "170,791", "Population3": "200,222"},
{"Name": "Mahe", "Status": "District", "Population1": "33,447", "Population2": "36,828", "Population3": "41,816"},
{"Name": "Puducherry", "Status": "District", "Population1": "608,338", "Population2": "735,332", "Population3": "950,289"},
{"Name": "Yanam", "Status": "District", "Population1": "20,297", "Population2": "31,394", "Population3": "55,626"},
{"Name": "Punjab", "Status": "State", "Population1": "20,281,969", "Population2": "24,358,999", "Population3": "27,743,338"},
{"Name": "Amritsar", "Status": "District", "Population1": "1,697,300", "Population2": "2,157,020", "Population3": "2,490,656"},
{"Name": "Barnala", "Status": "District", "Population1": "440,800", "Population2": "526,931", "Population3": "595,527"},
{"Name": "Bathinda", "Status": "District", "Population1": "985,300", "Population2": "1,183,295", "Population3": "1,388,525"},
{"Name": "Faridkot", "Status": "District", "Population1": "455,000", "Population2": "550,892", "Population3": "617,508"},
{"Name": "Fatehgarh Sahib", "Status": "District", "Population1": "455,300", "Population2": "538,470", "Population3": "600,163"},
{"Name": "Fazilka", "Status": " (", "Population1": ")", "Population2": "District", "Population3": "..."},
{"Name": "Firozpur", "Status": "District", "Population1": "...", "Population2": "719,712", "Population3": "825,629"},
{"Name": "Gurdaspur", "Status": "District", "Population1": "...", "Population2": "1,477,301", "Population3": "1,621,725"},
{"Name": "Hoshiarpur", "Status": "District", "Population1": "1,299,300", "Population2": "1,481,292", "Population3": "1,586,625"},
{"Name": "Jalandhar", "Status": "District", "Population1": "1,649,900", "Population2": "1,962,761", "Population3": "2,193,590"},
{"Name": "Kapurthala", "Status": "District", "Population1": "646,700", "Population2": "754,521", "Population3": "815,168"},
{"Name": "Ludhiana", "Status": "District", "Population1": "2,428,400", "Population2": "3,032,831", "Population3": "3,498,739"},
{"Name": "Mansa", "Status": "District", "Population1": "574,700", "Population2": "688,758", "Population3": "769,751"},
{"Name": "Moga", "Status": "District", "Population1": "777,900", "Population2": "894,793", "Population3": "995,746"},
{"Name": "Muktsar", "Status": "District", "Population1": "654,500", "Population2": "777,493", "Population3": "901,896"},
{"Name": "Pathankot", "Status": " (", "Population1": ")", "Population2": "District", "Population3": "..."},
{"Name": "Patiala", "Status": "District", "Population1": "1,344,900", "Population2": "1,584,780", "Population3": "1,895,686"},
{"Name": "Rupnagar", "Status": "District", "Population1": "542,700", "Population2": "628,846", "Population3": "684,627"},
{"Name": "Sahibzada Ajit Singh Nagar", "Status": "District", "Population1": "540,100", "Population2": "746,987", "Population3": "994,628"},
{"Name": "Sangrur", "Status": "District", "Population1": "1,244,700", "Population2": "1,473,242", "Population3": "1,655,169"},
{"Name": "Shahid Bhagat Singh Nagar", "Status": "District", "Population1": "531,300", "Population2": "587,468", "Population3": "612,310"},
{"Name": "Tarn Taran", "Status": "District", "Population1": "807,700", "Population2": "939,057", "Population3": "1,119,627"},
{"Name": "Rajasthan", "Status": "State", "Population1": "44,005,990", "Population2": "56,507,188", "Population3": "68,548,437"},
{"Name": "Ajmer", "Status": "District", "Population1": "1,726,600", "Population2": "2,178,447", "Population3": "2,583,052"},
{"Name": "Alwar", "Status": "District", "Population1": "2,295,600", "Population2": "2,991,552", "Population3": "3,674,179"},
{"Name": "Banswara", "Status": "District", "Population1": "1,096,000", "Population2": "1,420,601", "Population3": "1,797,485"},
{"Name": "Baran", "Status": "District", "Population1": "810,300", "Population2": "1,021,473", "Population3": "1,222,755"},
{"Name": "Barmer", "Status": "District", "Population1": "1,435,222", "Population2": "1,964,835", "Population3": "2,603,751"},
{"Name": "Bharatpur", "Status": "District", "Population1": "1,650,600", "Population2": "2,100,020", "Population3": "2,548,462"},
{"Name": "Bhilwara", "Status": "District", "Population1": "1,599,000", "Population2": "2,020,969", "Population3": "2,408,523"},
{"Name": "Bikaner", "Status": "District", "Population1": "1,381,200", "Population2": "1,696,039", "Population3": "2,363,937"},
{"Name": "Bundi", "Status": "District", "Population1": "770,248", "Population2": "962,620", "Population3": "1,110,906"},
{"Name": "Chittaurgarh", "Status": "District", "Population1": "1,104,600", "Population2": "1,330,360", "Population3": "1,544,338"},
{"Name": "Churu", "Status": "District", "Population1": "1,373,200", "Population2": "1,902,110", "Population3": "2,039,547"},
{"Name": "Dausa", "Status": "District", "Population1": "999,300", "Population2": "1,323,002", "Population3": "1,634,409"},
{"Name": "Dhaulpur", "Status": "District", "Population1": "749,500", "Population2": "983,258", "Population3": "1,206,516"},
{"Name": "Dungarpur", "Status": "District", "Population1": "874,549", "Population2": "1,107,643", "Population3": "1,388,552"},
{"Name": "Ganganagar", "Status": "District", "Population1": "1,402,500", "Population2": "1,789,423", "Population3": "1,969,168"},
{"Name": "Hanumangarh", "Status": "District", "Population1": "1,220,400", "Population2": "1,518,005", "Population3": "1,774,692"},
{"Name": "Jaipur", "Status": "District", "Population1": "3,888,000", "Population2": "5,251,071", "Population3": "6,626,178"},
{"Name": "Jaisalmer", "Status": "District", "Population1": "344,517", "Population2": "508,247", "Population3": "669,919"},
{"Name": "Jalor", "Status": "District", "Population1": "1,142,563", "Population2": "1,448,940", "Population3": "1,828,730"},
{"Name": "Jhalawar", "Status": "District", "Population1": "956,971", "Population2": "1,180,323", "Population3": "1,411,129"},
{"Name": "Jhunjhunu", "Status": "District", "Population1": "1,582,421", "Population2": "1,913,689", "Population3": "2,137,045"},
{"Name": "Jodhpur", "Status": "District", "Population1": "2,153,483", "Population2": "2,886,505", "Population3": "3,687,165"},
{"Name": "Karauli", "Status": "District", "Population1": "924,700", "Population2": "1,205,888", "Population3": "1,458,248"},
{"Name": "Kota", "Status": "District", "Population1": "1,220,500", "Population2": "1,568,705", "Population3": "1,951,014"},
{"Name": "Nagaur", "Status": "District", "Population1": "2,144,810", "Population2": "2,775,058", "Population3": "3,307,743"},
{"Name": "Pali", "Status": "District", "Population1": "1,486,432", "Population2": "1,820,251", "Population3": "2,037,573"},
{"Name": "Pratapgarh", "Status": "District", "Population1": "553,900", "Population2": "706,807", "Population3": "867,848"},
{"Name": "Rajsamand", "Status": "District", "Population1": "819,000", "Population2": "982,523", "Population3": "1,156,597"},
{"Name": "Sawai Madhopur", "Status": "District", "Population1": "875,800", "Population2": "1,117,057", "Population3": "1,335,551"},
{"Name": "Sikar", "Status": "District", "Population1": "1,842,914", "Population2": "2,287,788", "Population3": "2,677,333"},
{"Name": "Sirohi", "Status": "District", "Population1": "654,029", "Population2": "851,107", "Population3": "1,036,346"},
{"Name": "Tonk", "Status": "District", "Population1": "975,006", "Population2": "1,211,671", "Population3": "1,421,326"},
{"Name": "Udaipur", "Status": "District", "Population1": "1,952,300", "Population2": "2,481,201", "Population3": "3,068,420"},
{"Name": "Sikkim", "Status": "State", "Population1": "406,457", "Population2": "540,851", "Population3": "610,577"},
{"Name": "East District", "Status": "District", "Population1": "178,452", "Population2": "245,040", "Population3": "283,583"},
{"Name": "North  District", "Status": "District", "Population1": "31,240", "Population2": "41,030", "Population3": "43,709"},
{"Name": "South District", "Status": "District", "Population1": "98,604", "Population2": "131,525", "Population3": "146,850"},
{"Name": "West District", "Status": "District", "Population1": "98,161", "Population2": "123,256", "Population3": "136,435"},
{"Name": "Tamil Nadu", "Status": "State", "Population1": "55,858,946", "Population2": "62,405,679", "Population3": "72,147,030"},
{"Name": "Ariyalur", "Status": "District", "Population1": "636,400", "Population2": "695,524", "Population3": "754,894"},
{"Name": "Chennai", "Status": "District", "Population1": "3,841,396", "Population2": "4,343,645", "Population3": "4,646,732"},
{"Name": "Coimbatore", "Status": "District", "Population1": "2,493,700", "Population2": "2,916,620", "Population3": "3,458,045"},
{"Name": "Cuddalore", "Status": "District", "Population1": "2,122,759", "Population2": "2,285,395", "Population3": "2,605,914"},
{"Name": "Dharmapuri", "Status": "District", "Population1": "1,123,600", "Population2": "1,295,182", "Population3": "1,506,843"},
{"Name": "Dindigul", "Status": "District", "Population1": "1,760,601", "Population2": "1,923,014", "Population3": "2,159,775"},
{"Name": "Erode", "Status": "District", "Population1": "1,802,900", "Population2": "2,016,582", "Population3": "2,251,744"},
{"Name": "Kanchipuram", "Status": "District", "Population1": "2,415,000", "Population2": "2,877,468", "Population3": "3,998,252"},
{"Name": "Kanniyakumari", "Status": "District", "Population1": "1,600,349", "Population2": "1,676,034", "Population3": "1,870,374"},
{"Name": "Karur", "Status": "District", "Population1": "854,162", "Population2": "935,686", "Population3": "1,064,493"},
{"Name": "Krishnagiri", "Status": "District", "Population1": "1,305,100", "Population2": "1,561,118", "Population3": "1,879,809"},
{"Name": "Madurai", "Status": "District", "Population1": "2,400,339", "Population2": "2,578,201", "Population3": "3,038,252"},
{"Name": "Nagapattinam", "Status": "District", "Population1": "1,377,700", "Population2": "1,488,839", "Population3": "1,616,450"},
{"Name": "Namakkal", "Status": "District", "Population1": "1,322,715", "Population2": "1,493,462", "Population3": "1,726,601"},
{"Name": "Perambalur", "Status": "District", "Population1": "451,000", "Population2": "493,646", "Population3": "565,223"},
{"Name": "Pudukkottai", "Status": "District", "Population1": "1,327,148", "Population2": "1,459,601", "Population3": "1,618,345"},
{"Name": "Ramanathapuram", "Status": "District", "Population1": "1,119,100", "Population2": "1,187,604", "Population3": "1,353,445"},
{"Name": "Salem", "Status": "District", "Population1": "2,573,667", "Population2": "3,016,346", "Population3": "3,482,056"},
{"Name": "Sivaganga", "Status": "District", "Population1": "1,103,100", "Population2": "1,155,356", "Population3": "1,339,101"},
{"Name": "Thanjavur", "Status": "District", "Population1": "2,053,700", "Population2": "2,216,138", "Population3": "2,405,890"},
{"Name": "Theni", "Status": "District", "Population1": "1,049,323", "Population2": "1,093,950", "Population3": "1,245,899"},
{"Name": "The Nilgiris", "Status": "District", "Population1": "710,214", "Population2": "762,141", "Population3": "735,394"},
{"Name": "Thiruvallur", "Status": "District", "Population1": "2,238,500", "Population2": "2,754,756", "Population3": "3,728,104"},
{"Name": "Thiruvarur", "Status": "District", "Population1": "1,100,100", "Population2": "1,169,474", "Population3": "1,264,277"},
{"Name": "Thoothukkudi", "Status": "District", "Population1": "1,475,900", "Population2": "1,592,769", "Population3": "1,750,176"},
{"Name": "Tiruchirappalli", "Status": "District", "Population1": "2,196,473", "Population2": "2,418,366", "Population3": "2,722,290"},
{"Name": "Tirunelveli", "Status": "District", "Population1": "2,481,900", "Population2": "2,703,492", "Population3": "3,077,233"},
{"Name": "Tiruppur", "Status": "District", "Population1": "1,532,000", "Population2": "1,920,154", "Population3": "2,479,052"},
{"Name": "Tiruvannamalai", "Status": "District", "Population1": "2,042,979", "Population2": "2,186,125", "Population3": "2,464,875"},
{"Name": "Vellore", "Status": "District", "Population1": "3,026,432", "Population2": "3,477,317", "Population3": "3,936,331"},
{"Name": "Viluppuram", "Status": "District", "Population1": "2,755,674", "Population2": "2,960,373", "Population3": "3,458,873"},
{"Name": "Virudhunagar", "Status": "District", "Population1": "1,565,037", "Population2": "1,751,301", "Population3": "1,942,288"},
{"Name": "Telangana", "Status": "State", "Population1": "26,089,074", "Population2": "30,812,938", "Population3": "35,003,674"},
{"Name": "Adilabad", "Status": "District", "Population1": "...", "Population2": "608,018", "Population3": "708,972"},
{"Name": "Bhadradri Kothagudem", "Status": " (", "Population1": ")", "Population2": "District", "Population3": "..."},
{"Name": "Hyderabad", "Status": "District", "Population1": "3,145,939", "Population2": "3,829,753", "Population3": "3,943,323"},
{"Name": "Jagtial", "Status": " (", "Population1": ")", "Population2": "District", "Population3": "..."},
{"Name": "Jangaon", "Status": " (", "Population1": ")", "Population2": "District", "Population3": "..."},
{"Name": "Jayashankar Bhupalpally", "Status": " (", "Population1": ")", "Population2": "District", "Population3": "..."},
{"Name": "Jogulamba Gadwal", "Status": " (", "Population1": ")", "Population2": "District", "Population3": "..."},
{"Name": "Kamareddy", "Status": " (", "Population1": ")", "Population2": "District", "Population3": "..."},
{"Name": "Karimnagar", "Status": "District", "Population1": "...", "Population2": "901,300", "Population3": "1,005,711"},
{"Name": "Khammam", "Status": "District", "Population1": "...", "Population2": "1,279,996", "Population3": "1,401,639"},
{"Name": "Kumaram Bheem Asifabad", "Status": " (", "Population1": ")", "Population2": "District", "Population3": "..."},
{"Name": "Mahabubabad", "Status": " (", "Population1": ")", "Population2": "District", "Population3": "..."},
{"Name": "Mahabubnagar", "Status": "District", "Population1": "...", "Population2": "1,282,400", "Population3": "1,486,777"},
{"Name": "Mancherial", "Status": " (", "Population1": ")", "Population2": "District", "Population3": "..."},
{"Name": "Medak", "Status": "District", "Population1": "...", "Population2": "706,200", "Population3": "767,428"},
{"Name": "Medchal Malkajgiri", "Status": " (", "Population1": ")", "Population2": "District", "Population3": "..."},
{"Name": "Nagarkurnool", "Status": " (", "Population1": ")", "Population2": "District", "Population3": "..."},
{"Name": "Nalgonda", "Status": "District", "Population1": "...", "Population2": "1,474,894", "Population3": "1,618,416"},
{"Name": "Nirmal", "Status": " (", "Population1": ")", "Population2": "District", "Population3": "..."},
{"Name": "Nizamabad", "Status": "District", "Population1": "...", "Population2": "1,460,700", "Population3": "1,571,022"},
{"Name": "Peddapalli", "Status": " (", "Population1": ")", "Population2": "District", "Population3": "..."},
{"Name": "Rajanna Sircilla", "Status": " (", "Population1": ")", "Population2": "District", "Population3": "..."},
{"Name": "Rangareddy", "Status": "District", "Population1": "...", "Population2": "1,757,842", "Population3": "2,446,265"},
{"Name": "Sangareddy", "Status": " (", "Population1": ")", "Population2": "District", "Population3": "..."},
{"Name": "Siddipet", "Status": " (", "Population1": ")", "Population2": "District", "Population3": "..."},
{"Name": "Suryapet", "Status": " (", "Population1": ")", "Population2": "District", "Population3": "..."},
{"Name": "Vikarabad", "Status": " (", "Population1": ")", "Population2": "District", "Population3": "..."},
{"Name": "Wanaparthy", "Status": " (", "Population1": ")", "Population2": "District", "Population3": "..."},
{"Name": "Warangal Rural", "Status": " (", "Population1": ")", "Population2": "District", "Population3": "..."},
{"Name": "Warangal Urban", "Status": " (", "Population1": ")", "Population2": "District", "Population3": "..."},
{"Name": "Yadadri Bhuvanagiri", "Status": " (", "Population1": ")", "Population2": "District", "Population3": "..."},
{"Name": "Tripura", "Status": "State", "Population1": "2,757,205", "Population2": "3,199,203", "Population3": "3,673,917"},
{"Name": "Dhalai", "Status": "District", "Population1": "277,465", "Population2": "307,868", "Population3": "378,230"},
{"Name": "Gomati", "Status": " (", "Population1": ")", "Population2": "District", "Population3": "..."},
{"Name": "Khowai", "Status": " (", "Population1": ")", "Population2": "District", "Population3": "..."},
{"Name": "North Tripura", "Status": "District", "Population1": "...", "Population2": "359,144", "Population3": "417,441"},
{"Name": "Sipahijala", "Status": " (", "Population1": ")", "Population2": "District", "Population3": "..."},
{"Name": "South Tripura", "Status": "District", "Population1": "...", "Population2": "391,841", "Population3": "446,764"},
{"Name": "Unokoti", "Status": " (", "Population1": ")", "Population2": "District", "Population3": "..."},
{"Name": "West Tripura", "Status": "District", "Population1": "...", "Population2": "812,839", "Population3": "918,200"},
{"Name": "Uttarakhand", "Status": " (", "Population1": ")", "Population2": "State", "Population3": "7,113,483"},
{"Name": "Almora", "Status": "District", "Population1": "610,500", "Population2": "632,866", "Population3": "622,506"},
{"Name": "Bageshwar", "Status": "District", "Population1": "226,200", "Population2": "247,163", "Population3": "259,898"},
{"Name": "Chamoli", "Status": "District", "Population1": "325,311", "Population2": "370,359", "Population3": "391,605"},
{"Name": "Champawat", "Status": "District", "Population1": "190,900", "Population2": "224,542", "Population3": "259,648"},
{"Name": "Dehradun", "Status": "District", "Population1": "1,025,679", "Population2": "1,282,143", "Population3": "1,696,694"},
{"Name": "Garhwal", "Status": "District", "Population1": "670,800", "Population2": "697,078", "Population3": "687,271"},
{"Name": "Hardwar", "Status": "District", "Population1": "1,124,500", "Population2": "1,447,187", "Population3": "1,890,422"},
{"Name": "Nainital", "Status": "District", "Population1": "574,800", "Population2": "762,909", "Population3": "954,605"},
{"Name": "Pithoragarh", "Status": "District", "Population1": "416,647", "Population2": "462,289", "Population3": "483,439"},
{"Name": "Rudraprayag", "Status": "District", "Population1": "200,493", "Population2": "227,439", "Population3": "242,285"},
{"Name": "Tehri Garhwal", "Status": "District", "Population1": "520,214", "Population2": "604,747", "Population3": "618,931"},
{"Name": "Udham Singh Nagar", "Status": "District", "Population1": "924,900", "Population2": "1,235,614", "Population3": "1,648,902"},
{"Name": "Uttarkashi", "Status": "District", "Population1": "239,709", "Population2": "295,013", "Population3": "330,086"},
{"Name": "Uttar Pradesh", "Status": "State", "Population1": "131,998,804", "Population2": "166,197,921", "Population3": "199,812,341"},
{"Name": "Agra", "Status": "District", "Population1": "2,752,100", "Population2": "3,621,702", "Population3": "4,418,797"},
{"Name": "Aligarh", "Status": "District", "Population1": "2,450,000", "Population2": "2,992,286", "Population3": "3,673,889"},
{"Name": "Allahabad", "Status": "District", "Population1": "3,899,600", "Population2": "4,937,266", "Population3": "5,954,391"},
{"Name": "Ambedkar Nagar", "Status": "District", "Population1": "1,629,000", "Population2": "2,026,876", "Population3": "2,397,888"},
{"Name": "Amethi", "Status": " (", "Population1": ")", "Population2": "District", "Population3": "..."},
{"Name": "Amroha", "Status": "District", "Population1": "1,156,000", "Population2": "1,499,068", "Population3": "1,840,221"},
{"Name": "Auraiya", "Status": "District", "Population1": "1,028,000", "Population2": "1,179,993", "Population3": "1,379,545"},
{"Name": "Azamgarh", "Status": "District", "Population1": "3,129,000", "Population2": "3,939,916", "Population3": "4,613,913"},
{"Name": "Baghpat", "Status": "District", "Population1": "1,030,000", "Population2": "1,163,991", "Population3": "1,303,048"},
{"Name": "Bahraich", "Status": "District", "Population1": "2,090,900", "Population2": "2,701,478", "Population3": "3,487,731"},
{"Name": "Ballia", "Status": "District", "Population1": "2,261,500", "Population2": "2,760,667", "Population3": "3,239,774"},
{"Name": "Balrampur", "Status": "District", "Population1": "1,369,000", "Population2": "1,682,350", "Population3": "2,148,665"},
{"Name": "Banda", "Status": "District", "Population1": "1,237,900", "Population2": "1,501,602", "Population3": "1,799,410"},
{"Name": "Bara Banki", "Status": "District", "Population1": "2,115,000", "Population2": "2,673,581", "Population3": "3,260,699"},
{"Name": "Bareilly", "Status": "District", "Population1": "2,834,616", "Population2": "3,618,589", "Population3": "4,448,359"},
{"Name": "Basti", "Status": "District", "Population1": "1,686,000", "Population2": "2,084,814", "Population3": "2,464,464"},
{"Name": "Bhadohi", "Status": " (", "Population1": ")", "Population2": "District", "Population3": "1,078,000"},
{"Name": "Bijnor", "Status": "District", "Population1": "2,462,000", "Population2": "3,131,619", "Population3": "3,682,713"},
{"Name": "Budaun", "Status": "District", "Population1": "...", "Population2": "2,630,710", "Population3": "3,127,621"},
{"Name": "Bulandshahr", "Status": "District", "Population1": "2,547,100", "Population2": "3,009,860", "Population3": "3,499,171"},
{"Name": "Chandauli", "Status": "District", "Population1": "1,275,000", "Population2": "1,643,251", "Population3": "1,952,756"},
{"Name": "Chitrakoot", "Status": "District", "Population1": "624,200", "Population2": "801,957", "Population3": "991,730"},
{"Name": "Deoria", "Status": "District", "Population1": "2,185,000", "Population2": "2,714,179", "Population3": "3,100,946"},
{"Name": "Etah", "Status": "District", "Population1": "1,229,900", "Population2": "1,531,645", "Population3": "1,774,480"},
{"Name": "Etawah", "Status": "District", "Population1": "1,102,000", "Population2": "1,338,871", "Population3": "1,581,810"},
{"Name": "Faizabad", "Status": "District", "Population1": "1,686,000", "Population2": "2,088,928", "Population3": "2,470,996"},
{"Name": "Farrukhabad", "Status": "District", "Population1": "1,284,000", "Population2": "1,570,408", "Population3": "1,885,204"},
{"Name": "Fatehpur", "Status": "District", "Population1": "1,899,241", "Population2": "2,308,384", "Population3": "2,632,733"},
{"Name": "Firozabad", "Status": "District", "Population1": "1,555,600", "Population2": "2,081,752", "Population3": "2,498,156"},
{"Name": "Gautam Buddha Nagar", "Status": "District", "Population1": "771,000", "Population2": "1,105,292", "Population3": "1,648,115"},
{"Name": "Ghaziabad", "Status": "District", "Population1": "...", "Population2": "2,184,930", "Population3": "3,343,334"},
{"Name": "Ghazipur", "Status": "District", "Population1": "2,416,617", "Population2": "3,037,582", "Population3": "3,620,268"},
{"Name": "Gonda", "Status": "District", "Population1": "2,205,000", "Population2": "2,765,586", "Population3": "3,433,919"},
{"Name": "Gorakhpur", "Status": "District", "Population1": "3,066,002", "Population2": "3,769,456", "Population3": "4,440,895"},
{"Name": "Hamirpur", "Status": "District", "Population1": "841,400", "Population2": "993,792", "Population3": "1,104,285"},
{"Name": "Hapur", "Status": " (", "Population1": ")", "Population2": "District", "Population3": "..."},
{"Name": "Hardoi", "Status": "District", "Population1": "2,747,082", "Population2": "3,398,306", "Population3": "4,092,845"},
{"Name": "Hathras", "Status": " (", "Population1": ")", "Population2": "District", "Population3": "1,127,000"},
{"Name": "Jalaun", "Status": "District", "Population1": "1,219,377", "Population2": "1,454,452", "Population3": "1,689,974"},
{"Name": "Jaunpur", "Status": "District", "Population1": "3,214,636", "Population2": "3,911,679", "Population3": "4,494,204"},
{"Name": "Jhansi", "Status": "District", "Population1": "1,417,000", "Population2": "1,744,931", "Population3": "1,998,603"},
{"Name": "Kannauj", "Status": "District", "Population1": "1,158,000", "Population2": "1,388,923", "Population3": "1,656,616"},
{"Name": "Kanpur Dehat", "Status": "District", "Population1": "1,303,000", "Population2": "1,563,336", "Population3": "1,796,184"},
{"Name": "Kanpur Nagar", "Status": "District", "Population1": "3,254,000", "Population2": "4,167,999", "Population3": "4,581,268"},
{"Name": "Kasganj", "Status": "District", "Population1": "991,300", "Population2": "1,228,705", "Population3": "1,436,719"},
{"Name": "Kaushambi", "Status": "District", "Population1": "1,021,700", "Population2": "1,291,993", "Population3": "1,599,596"},
{"Name": "Kheri", "Status": "District", "Population1": "2,419,234", "Population2": "3,207,232", "Population3": "4,021,243"},
{"Name": "Kushinagar", "Status": "District", "Population1": "2,255,100", "Population2": "2,891,667", "Population3": "3,564,544"},
{"Name": "Lalitpur", "Status": "District", "Population1": "752,043", "Population2": "977,734", "Population3": "1,221,592"},
{"Name": "Lucknow", "Status": "District", "Population1": "2,762,801", "Population2": "3,647,834", "Population3": "4,589,838"},
{"Name": "Mahoba", "Status": "District", "Population1": "625,100", "Population2": "758,379", "Population3": "875,958"},
{"Name": "Mahrajganj", "Status": "District", "Population1": "1,676,378", "Population2": "2,173,878", "Population3": "2,684,703"},
{"Name": "Mainpuri", "Status": "District", "Population1": "1,311,000", "Population2": "1,596,718", "Population3": "1,868,529"},
{"Name": "Mathura", "Status": "District", "Population1": "1,630,000", "Population2": "2,074,516", "Population3": "2,547,184"},
{"Name": "Mau", "Status": "District", "Population1": "1,446,600", "Population2": "1,854,950", "Population3": "2,205,968"},
{"Name": "Meerut", "Status": "District", "Population1": "2,397,100", "Population2": "2,973,877", "Population3": "3,443,689"},
{"Name": "Mirzapur", "Status": "District", "Population1": "1,628,000", "Population2": "2,074,709", "Population3": "2,496,970"},
{"Name": "Moradabad", "Status": "District", "Population1": "...", "Population2": "2,467,960", "Population3": "3,126,507"},
{"Name": "Muzaffarnagar", "Status": "District", "Population1": "...", "Population2": "2,438,565", "Population3": "2,869,934"},
{"Name": "Pilibhit", "Status": "District", "Population1": "1,343,800", "Population2": "1,728,108", "Population3": "2,031,007"},
{"Name": "Pratapgarh", "Status": "District", "Population1": "2,210,700", "Population2": "2,731,174", "Population3": "3,209,141"},
{"Name": "Rae Bareli", "Status": "District", "Population1": "...", "Population2": "2,053,728", "Population3": "2,403,705"},
{"Name": "Rampur", "Status": "District", "Population1": "1,502,141", "Population2": "1,923,739", "Population3": "2,335,819"},
{"Name": "Saharanpur", "Status": "District", "Population1": "2,309,029", "Population2": "2,896,863", "Population3": "3,466,382"},
{"Name": "Sambhal", "Status": " (", "Population1": ")", "Population2": "District", "Population3": "..."},
{"Name": "Sant Kabir Nagar", "Status": "District", "Population1": "1,152,000", "Population2": "1,420,226", "Population3": "1,715,183"},
{"Name": "Shahjahanpur", "Status": "District", "Population1": "1,926,600", "Population2": "2,464,930", "Population3": "3,006,538"},
{"Name": "Shamli", "Status": " (", "Population1": ")", "Population2": "District", "Population3": "..."},
{"Name": "Shrawasti", "Status": "District", "Population1": "672,900", "Population2": "855,985", "Population3": "1,117,361"},
{"Name": "Siddharthnagar", "Status": "District", "Population1": "1,608,000", "Population2": "2,040,085", "Population3": "2,559,297"},
{"Name": "Sitapur", "Status": "District", "Population1": "2,857,009", "Population2": "3,619,661", "Population3": "4,483,992"},
{"Name": "Sonbhadra", "Status": "District", "Population1": "1,104,200", "Population2": "1,504,852", "Population3": "1,862,559"},
{"Name": "Sultanpur", "Status": "District", "Population1": "...", "Population2": "1,901,332", "Population3": "2,249,036"},
{"Name": "Unnao", "Status": "District", "Population1": "2,200,397", "Population2": "2,700,324", "Population3": "3,108,367"},
{"Name": "Varanasi", "Status": "District", "Population1": "2,508,000", "Population2": "3,138,671", "Population3": "3,676,841"},
{"Name": "West Bengal", "Status": "State", "Population1": "68,077,965", "Population2": "80,176,197", "Population3": "91,276,115"},
{"Name": "Alipurduar", "Status": " (", "Population1": ")", "Population2": "District", "Population3": "..."},
{"Name": "Bankura", "Status": "District", "Population1": "2,805,065", "Population2": "3,192,695", "Population3": "3,596,674"},
{"Name": "Birbhum", "Status": "District", "Population1": "2,555,664", "Population2": "3,015,422", "Population3": "3,502,404"},
{"Name": "Cooch Behar", "Status": " (", "Population1": ")", "Population2": "District", "Population3": "2,171,145"},
{"Name": "Dakshin Dinajpur", "Status": "District", "Population1": "1,230,608", "Population2": "1,503,178", "Population3": "1,676,276"},
{"Name": "Darjiling", "Status": "District", "Population1": "...", "Population2": "1,383,952", "Population3": "1,595,181"},
{"Name": "Hooghly", "Status": " (", "Population1": ")", "Population2": "District", "Population3": "4,355,230"},
{"Name": "Howrah", "Status": " (", "Population1": ")", "Population2": "District", "Population3": "3,729,644"},
{"Name": "Jalpaiguri", "Status": "District", "Population1": "...", "Population2": "2,063,598", "Population3": "2,381,596"},
{"Name": "Jhargram", "Status": " (", "Population1": ")", "Population2": "District", "Population3": "..."},
{"Name": "Kalimpong", "Status": " (", "Population1": ")", "Population2": "District", "Population3": "..."},
{"Name": "Kolkata", "Status": "District", "Population1": "4,399,819", "Population2": "4,572,876", "Population3": "4,496,694"},
{"Name": "Maldah", "Status": "District", "Population1": "2,637,032", "Population2": "3,290,468", "Population3": "3,988,845"},
{"Name": "Murshidabad", "Status": "District", "Population1": "4,740,149", "Population2": "5,866,569", "Population3": "7,103,807"},
{"Name": "Nadia", "Status": "District", "Population1": "3,852,097", "Population2": "4,604,827", "Population3": "5,167,600"},
{"Name": "North Twenty Four Parganas", "Status": "District", "Population1": "7,281,881", "Population2": "8,934,286", "Population3": "10,009,781"},
{"Name": "Paschim Bardhaman", "Status": " (", "Population1": ")", "Population2": "District", "Population3": "..."},
{"Name": "Paschim Medinipur", "Status": "District", "Population1": "...", "Population2": "4,185,381", "Population3": "4,776,909"},
{"Name": "Purba Bardhaman", "Status": " (", "Population1": ")", "Population2": "District", "Population3": "..."},
{"Name": "Purba Medinipur", "Status": "District", "Population1": "3,845,545", "Population2": "4,417,377", "Population3": "5,095,875"},
{"Name": "Puruliya", "Status": "District", "Population1": "2,224,577", "Population2": "2,536,516", "Population3": "2,930,115"},
{"Name": "South Twenty Four Parganas", "Status": "District", "Population1": "5,715,030", "Population2": "6,906,689", "Population3": "8,161,961"},
{"Name": "Uttar Dinajpur", "Status": "District", "Population1": "1,897,045", "Population2": "2,441,794", "Population3": "3,007,134"}
]